dermalytics/__init__.py
dermalytics/client.py
dermalytics/exceptions.py
dermalytics/types.py
dermalytics-0.1.3.dist-info/licenses/LICENSE
dermalytics-0.1.3.dist-info/METADATA
dermalytics-0.1.3.dist-info/WHEEL
dermalytics-0.1.3.dist-info/top_level.txt
dermalytics-0.1.3.dist-info/RECORD
