Metadata-Version: 2.4
Name: dermalytics
Version: 0.1.3
Summary: Python SDK for the Dermalytics API - Skincare Ingredient Analysis
Home-page: https://github.com/dermalytics-dev/dermalytics-python
Author: Dermalytics
Author-email: Dermalytics <support@dermalytics.dev>
License: MIT
Project-URL: Homepage, https://github.com/dermalytics-dev/dermalytics-python
Project-URL: Documentation, https://docs.dermalytics.dev
Project-URL: Repository, https://github.com/dermalytics-dev/dermalytics-python
Project-URL: Issues, https://github.com/dermalytics-dev/dermalytics-python/issues
Keywords: skincare,ingredients,api,dermatology,cosmetics
Classifier: Development Status :: 3 - Alpha
Classifier: Intended Audience :: Developers
Classifier: License :: OSI Approved :: MIT License
Classifier: Operating System :: OS Independent
Classifier: Programming Language :: Python :: 3
Classifier: Programming Language :: Python :: 3.8
Classifier: Programming Language :: Python :: 3.9
Classifier: Programming Language :: Python :: 3.10
Classifier: Programming Language :: Python :: 3.11
Classifier: Programming Language :: Python :: 3.12
Classifier: Programming Language :: Python :: 3.13
Classifier: Programming Language :: Python :: 3.14
Classifier: Topic :: Software Development :: Libraries :: Python Modules
Requires-Python: >=3.8
License-File: LICENSE
Requires-Dist: requests>=2.31.0
Dynamic: author
Dynamic: home-page
Dynamic: license-file
Dynamic: requires-python
